LICENSE
MANIFEST.in
README.rst
setup.py
django_postgun.egg-info/PKG-INFO
django_postgun.egg-info/SOURCES.txt
django_postgun.egg-info/dependency_links.txt
django_postgun.egg-info/requires.txt
django_postgun.egg-info/top_level.txt
postgun/__init__.py
postgun/backends.py
postgun/events.py
postgun/message.py
postgun/models.py
postgun/validators.py
postgun/migrations/__init__.py
postgun/migrations/__init__.pyc
postgun/tests/__init__.py
postgun/tests/tests_postgun.py