Metadata-Version: 1.1
Name: django-postgun
Version: 0.3
Summary: Send email using Mailgun with Mailgun specific attributes.
Home-page: https://bitbucket.org/jamesvandyne/postgun
Author: James Van Dyne
Author-email: james@sugoisoft.com
License: BSD License
Platform: UNKNOWN
Classifier: Environment :: Web Environment
Classifier: Framework :: Django
Classifier: Intended Audience :: Developers
Classifier: License :: OSI Approved :: BSD License
Classifier: Operating System :: OS Independent
Classifier: Programming Language :: Python
Classifier: Programming Language :: Python :: 2.7
Classifier: Topic :: Internet :: WWW/HTTP
Classifier: Topic :: Internet :: WWW/HTTP :: Dynamic Content
Classifier: Development Status :: 4 - Beta
